airtasks/__init__.py
airtasks/main.py
airtasks-0.1.0.dist-info/WHEEL
airtasks-0.1.0.dist-info/METADATA
airtasks-0.1.0.dist-info/RECORD
