Metadata-Version: 2.3
Name: airtasks
Version: 0.1.0
Summary: Generic background task handling for Air applications
Author: Ian Flath
Author-email: Ian Flath <ian@kentro.tech>
Requires-Dist: fastapi[standard]>=0.121.1
Requires-Dist: loguru>=0.7.0
Requires-Python: >=3.13
Project-URL: Homepage, https://github.com/kentro-tech/airtasks
Project-URL: Issues, https://github.com/kentro-tech/airtasks/issues
